drawzero/__about__.py
drawzero/__init__.py
drawzero/__main__.py
drawzero/examples/00_hello_world.py
drawzero/examples/01_grid_and_coordinates.py
drawzero/examples/02_loops_and_rgb_colors.py
drawzero/examples/03_simple_objects.py
drawzero/examples/04_loops_sin_plot.py
drawzero/examples/05_points.py
drawzero/examples/06_turtle_style.py
drawzero/examples/07_animation_circles.py
drawzero/examples/08_animation_traffic_light.py
drawzero/examples/09_animation_rectangles.py
drawzero/examples/10_animation_planets.py
drawzero/examples/11_transparency_and_line_width.py
drawzero/examples/12_images.py
drawzero/examples/13_gradients.py
drawzero/examples/14_animation_close_vertex.py
drawzero/examples/15_animation_firework.py
drawzero/examples/16_keyboard_and_mouse.py
drawzero/examples/17_mouse_tube.py
drawzero/examples/18_game_stars.py
drawzero/examples/19_game_colors.py
drawzero/examples/20_game_racing.py
drawzero/examples/99_errors.py
drawzero/examples/__init__.py
drawzero/examples/cat.png
drawzero/examples/dummy.py
drawzero/utils/__init__.py
drawzero/utils/colors.py
drawzero/utils/converters.py
drawzero/utils/copy_examples.py
drawzero/utils/draw.py
drawzero/utils/errors.py
drawzero/utils/gradient.py
drawzero/utils/i18n.py
drawzero/utils/key_flags.py
drawzero/utils/pt.py
drawzero/utils/renderer.py
drawzero/utils/renderer_ejudge.py
drawzero/utils/screen_size.py
drawzero-0.4.5.dist-info/LICENSE
drawzero-0.4.5.dist-info/METADATA
drawzero-0.4.5.dist-info/WHEEL
drawzero-0.4.5.dist-info/top_level.txt
drawzero-0.4.5.dist-info/RECORD
